a2a_client/__init__.py
a2a_client/client.py
a2a_client_172ai-1.1.0.dist-info/METADATA
a2a_client_172ai-1.1.0.dist-info/WHEEL
a2a_client_172ai-1.1.0.dist-info/top_level.txt
a2a_client_172ai-1.1.0.dist-info/RECORD
