Metadata-Version: 2.4
Name: a2a-client-172ai
Version: 1.1.0
Summary: Official Python client library for 172.ai A2A (Agent-to-Agent) communication
Home-page: https://github.com/172ai/a2a-client-python
Author: 172.ai
Author-email: support@172.ai
Keywords: 172ai a2a agent-to-agent container api-client sdlc
Classifier: Development Status :: 4 - Beta
Classifier: Intended Audience :: Developers
Classifier: Topic :: Software Development :: Libraries
Classifier: License :: OSI Approved :: MIT License
Classifier: Programming Language :: Python :: 3
Classifier: Programming Language :: Python :: 3.8
Classifier: Programming Language :: Python :: 3.9
Classifier: Programming Language :: Python :: 3.10
Classifier: Programming Language :: Python :: 3.11
Requires-Python: >=3.8
Requires-Dist: requests>=2.28.0
Dynamic: author
Dynamic: author-email
Dynamic: classifier
Dynamic: description
Dynamic: description-content-type
Dynamic: home-page
Dynamic: keywords
Dynamic: requires-dist
Dynamic: requires-python
Dynamic: summary
